olbrain/__init__.py
olbrain/client.py
olbrain/exceptions.py
olbrain/session.py
olbrain/streaming.py
olbrain/utils.py
olbrain_python_sdk-0.3.0.dist-info/licenses/LICENSE
tests/__init__.py
tests/test_client.py
tests/test_exceptions.py
tests/test_session.py
olbrain_python_sdk-0.3.0.dist-info/METADATA
olbrain_python_sdk-0.3.0.dist-info/WHEEL
olbrain_python_sdk-0.3.0.dist-info/top_level.txt
olbrain_python_sdk-0.3.0.dist-info/RECORD
