Metadata-Version: 2.4
Name: olbrain-python-sdk
Version: 0.3.0
Summary: Official Python SDK for Olbrain AI agents
Home-page: https://github.com/Olbrain/olbrain-python-sdk
Author: Olbrain Team
Author-email: Olbrain Team <support@olbrain.com>
License: MIT
Project-URL: Homepage, https://github.com/Olbrain/olbrain-python-sdk
Project-URL: Bug Reports, https://github.com/Olbrain/olbrain-python-sdk/issues
Project-URL: Source, https://github.com/Olbrain/olbrain-python-sdk
Project-URL: Documentation, https://docs.olbrain.com/python-sdk
Keywords: olbrain,ai,agents,chatbot,nlp,artificial intelligence,sdk,api,conversation,streaming
Classifier: Development Status :: 4 - Beta
Classifier: Intended Audience :: Developers
Classifier: License :: OSI Approved :: MIT License
Classifier: Operating System :: OS Independent
Classifier: Programming Language :: Python :: 3
Classifier: Programming Language :: Python :: 3.7
Classifier: Programming Language :: Python :: 3.8
Classifier: Programming Language :: Python :: 3.9
Classifier: Programming Language :: Python :: 3.10
Classifier: Programming Language :: Python :: 3.11
Classifier: Programming Language :: Python :: 3.12
Classifier: Topic :: Software Development :: Libraries :: Python Modules
Classifier: Topic :: Scientific/Engineering :: Artificial Intelligence
Classifier: Topic :: Internet :: WWW/HTTP :: Dynamic Content
Requires-Python: >=3.7
License-File: LICENSE
Requires-Dist: requests>=2.25.0
Requires-Dist: urllib3>=1.26.0
Provides-Extra: dev
Requires-Dist: pytest>=6.0.0; extra == "dev"
Requires-Dist: pytest-asyncio>=0.18.0; extra == "dev"
Requires-Dist: pytest-cov>=2.12.0; extra == "dev"
Requires-Dist: black>=22.0.0; extra == "dev"
Requires-Dist: flake8>=4.0.0; extra == "dev"
Requires-Dist: mypy>=0.910; extra == "dev"
Requires-Dist: requests-mock>=1.9.0; extra == "dev"
Provides-Extra: async
Requires-Dist: aiohttp>=3.8.0; extra == "async"
Requires-Dist: aiofiles>=0.7.0; extra == "async"
Dynamic: author
Dynamic: home-page
Dynamic: license-file
Dynamic: requires-python
